exception_convenience/__init__.py
exception_convenience-0.1.0.dist-info/LICENSE
exception_convenience-0.1.0.dist-info/METADATA
exception_convenience-0.1.0.dist-info/WHEEL
exception_convenience-0.1.0.dist-info/top_level.txt
exception_convenience-0.1.0.dist-info/RECORD
